opack/__init__.py
opack/exceptions.py
opack/object_types.py
opack/opack.py
opack/opack_construct.py
opack-0.1.0.dist-info/LICENSE
opack-0.1.0.dist-info/METADATA
opack-0.1.0.dist-info/WHEEL
opack-0.1.0.dist-info/entry_points.txt
opack-0.1.0.dist-info/top_level.txt
opack-0.1.0.dist-info/RECORD
