Metadata-Version: 2.1
Name: opack
Version: 0.1.0
Summary: Python library for parsing the opack format
Author-email: lori <loriwittdev@gmail.com>
Maintainer-email: lori <loriwittdev@gmail.com>
License: MIT License
Project-URL: Homepage, https://github.com/loriwitt/opack
Project-URL: Bug Reports, https://github.com/loriwitt/opack/issues
Keywords: ios,opack,plist,cli,parser
Classifier: Development Status :: 5 - Production/Stable
Classifier: License :: OSI Approved :: GNU General Public License v3 or later (GPLv3+)
Classifier: Programming Language :: Python :: 3
Classifier: Programming Language :: Python :: 3.8
Classifier: Programming Language :: Python :: 3.9
Classifier: Programming Language :: Python :: 3.10
Classifier: Programming Language :: Python :: 3.11
Classifier: Programming Language :: Python :: 3 :: Only
Requires-Python: >=3.8
Provides-Extra: test
License-File: LICENSE
